{
  "last_updated": "2026-02-09T15:21:18.448437+00:00",
  "stream_count": 16,
  "streams": [
    {
      "temple_id": "shirdi_sai",
      "temple_name": "Shirdi Sai Baba",
      "video_id": "qsO4T724XDI",
      "url": "https://www.youtube.com/watch?v=qsO4T724XDI",
      "embed_url": "https://www.youtube.com/embed/qsO4T724XDI",
      "title": "🔴Live Shirdi SaiBaba Darshan - 9 February 2026",
      "channel": "The Real SoulShirdi Sai",
      "channel_id": "UCstmnfIOcvO-6DONnfKhAPg",
      "viewer_count": 176,
      "is_trusted_channel": true,
      "stream_started_at": "2026-02-09T10:26:18Z",
      "published_at": "2026-02-09T10:20:08Z",
      "thumbnail": "https://i.ytimg.com/vi/qsO4T724XDI/hqdefault_live.jpg"
    },
    {
      "temple_id": "somnath",
      "temple_name": "Somnath Temple",
      "video_id": "xlu0vLqNejw",
      "url": "https://www.youtube.com/watch?v=xlu0vLqNejw",
      "embed_url": "https://www.youtube.com/embed/xlu0vLqNejw",
      "title": "🔴 Live Darshan - Shree Somnath Temple, First Jyotirlinga - 09- February-2026",
      "channel": "Somnath Temple - Official Channel",
      "channel_id": "UCT1egsvA08YcdMLiEu1DTRg",
      "viewer_count": 111,
      "is_trusted_channel": true,
      "stream_started_at": "2026-02-09T09:17:05Z",
      "published_at": "2026-02-09T08:39:51Z",
      "thumbnail": "https://i.ytimg.com/vi/xlu0vLqNejw/hqdefault_live.jpg"
    },
    {
      "temple_id": "salasar",
      "temple_name": "Salasar Balaji",
      "video_id": "SrDCZCWmz1U",
      "url": "https://www.youtube.com/watch?v=SrDCZCWmz1U",
      "embed_url": "https://www.youtube.com/embed/SrDCZCWmz1U",
      "title": "🔴 Live :  Live Darshan 02 Shree KasthBhanjandev Hanumanji Mandir Salangpur",
      "channel": "Salangpur Hanumanji - Official",
      "channel_id": "UCI1r_MNxzyvUPHyTdWDe4NA",
      "viewer_count": 128,
      "is_trusted_channel": false,
      "stream_started_at": "2026-01-05T10:57:13Z",
      "published_at": "2026-01-05T10:54:16Z",
      "thumbnail": "https://i.ytimg.com/vi/SrDCZCWmz1U/hqdefault_live.jpg"
    },
    {
      "temple_id": "dwarkadhish",
      "temple_name": "Dwarkadhish Temple",
      "video_id": "kcbDdLnZvBA",
      "url": "https://www.youtube.com/watch?v=kcbDdLnZvBA",
      "embed_url": "https://www.youtube.com/embed/kcbDdLnZvBA",
      "title": "Shri Dwarkadhish Mandir",
      "channel": "Shri Dwarkadhish Mandir",
      "channel_id": "UCBAvMHZO3BIfMMhOK9LMOYQ",
      "viewer_count": 1172,
      "is_trusted_channel": true,
      "stream_started_at": "2026-02-09T11:20:15Z",
      "published_at": "2026-02-09T11:19:48Z",
      "thumbnail": "https://i.ytimg.com/vi/kcbDdLnZvBA/hqdefault_live.jpg"
    },
    {
      "temple_id": "radhavallabh",
      "temple_name": "Shri Radhavallabh Mandir",
      "video_id": "oa13udiArEE",
      "url": "https://www.youtube.com/watch?v=oa13udiArEE",
      "embed_url": "https://www.youtube.com/embed/oa13udiArEE",
      "title": "Live : Shri RadhaVallabh Mandir Daily Live Darshan Vrindavan",
      "channel": "Shri Radhavallabh Mandir",
      "channel_id": "UCTw4wtqF6KEA8ULDSi_6fUQ",
      "viewer_count": 30,
      "is_trusted_channel": true,
      "stream_started_at": "2026-02-09T11:34:36Z",
      "published_at": "2026-02-09T11:02:20Z",
      "thumbnail": "https://i.ytimg.com/vi/oa13udiArEE/hqdefault_live.jpg"
    },
    {
      "temple_id": "mahakal",
      "temple_name": "Mahakaleshwar Ujjain",
      "video_id": "qeuOpk3qgE8",
      "url": "https://www.youtube.com/watch?v=qeuOpk3qgE8",
      "embed_url": "https://www.youtube.com/embed/qeuOpk3qgE8",
      "title": "09 February 2026 सोमवार संध्या आरती | श्री महाकालेश्वर ज्योतिर्लिंग | Live Monday Sandhya Aarti",
      "channel": "Mahakaleshwar Jyotirlinga Live Darshan",
      "channel_id": "UC7q12ONY2mvuq066rreluhQ",
      "viewer_count": 40,
      "is_trusted_channel": true,
      "stream_started_at": "2026-02-08T22:46:01Z",
      "published_at": "2026-02-08T22:45:11Z",
      "thumbnail": "https://i.ytimg.com/vi/qeuOpk3qgE8/hqdefault_live.jpg"
    },
    {
      "temple_id": "mahalakshmi",
      "temple_name": "Mahalakshmi Temple Mumbai",
      "video_id": "oKVtWNV88vI",
      "url": "https://www.youtube.com/watch?v=oKVtWNV88vI",
      "embed_url": "https://www.youtube.com/embed/oKVtWNV88vI",
      "title": "Shri Mahalakshmi Mandir Mumbai Official Live Stream",
      "channel": "Shree Mahalakshmi Mandir Mumbai Official",
      "channel_id": "UCqNGTFK0_nHU2Ldj3ZKScYw",
      "viewer_count": 19,
      "is_trusted_channel": true,
      "stream_started_at": "2026-02-08T16:26:52Z",
      "published_at": "2026-02-08T16:26:27Z",
      "thumbnail": "https://i.ytimg.com/vi/oKVtWNV88vI/hqdefault_live.jpg"
    },
    {
      "temple_id": "siddhivinayak",
      "temple_name": "Siddhivinayak Mumbai",
      "video_id": "vbXFCEZHfVU",
      "url": "https://www.youtube.com/watch?v=vbXFCEZHfVU",
      "embed_url": "https://www.youtube.com/embed/vbXFCEZHfVU",
      "title": "LIVE : Siddhivinayak Live Darshan || सिद्धिविनायक लाइव दर्शन || From Siddhivinayak Mandir Mumbai2025",
      "channel": "Mayur Bhakti",
      "channel_id": "UCpSTRmTFY7pCzdeHJwAiAEg",
      "viewer_count": 9,
      "is_trusted_channel": false,
      "stream_started_at": "2026-02-09T10:46:42Z",
      "published_at": "2026-02-09T10:46:11Z",
      "thumbnail": "https://i.ytimg.com/vi/vbXFCEZHfVU/hqdefault_live.jpg"
    },
    {
      "temple_id": "naina_devi",
      "temple_name": "Naina Devi Temple",
      "video_id": "hIR-Zl8vVtI",
      "url": "https://www.youtube.com/watch?v=hIR-Zl8vVtI",
      "embed_url": "https://www.youtube.com/embed/hIR-Zl8vVtI",
      "title": "🔴 Shri  Naina Devi ji Temple , Bilaspur  (नैना देवी मंदिर हिमाचल प्रदेश)",
      "channel": "BHAKTI LIVE",
      "channel_id": "UCXhail7h5FDRbHprlR56nIw",
      "viewer_count": 6,
      "is_trusted_channel": true,
      "stream_started_at": "2025-07-30T00:38:19Z",
      "published_at": "2025-07-29T01:18:29Z",
      "thumbnail": "https://i.ytimg.com/vi/hIR-Zl8vVtI/hqdefault_live.jpg"
    },
    {
      "temple_id": "iskcon_juhu",
      "temple_name": "ISKCON Juhu Mumbai",
      "video_id": "tLJjwnXNeP8",
      "url": "https://www.youtube.com/watch?v=tLJjwnXNeP8",
      "embed_url": "https://www.youtube.com/embed/tLJjwnXNeP8",
      "title": "ISKCON Juhu Mumbai Live Darshan Part - 2  | 9th Feb 2026 ( 3 : 30 PM to 9 PM )",
      "channel": "ISKCON Juhu Mumbai",
      "channel_id": "UC1vJ4RlWSHP6n0xL2G1tkYQ",
      "viewer_count": 64,
      "is_trusted_channel": true,
      "stream_started_at": "2026-02-09T10:16:34Z",
      "published_at": "2026-02-05T11:41:53Z",
      "thumbnail": "https://i.ytimg.com/vi/tLJjwnXNeP8/hqdefault_live.jpg"
    },
    {
      "temple_id": "pashupatinath",
      "temple_name": "Pashupatinath Temple",
      "video_id": "cWlagqX0BJQ",
      "url": "https://www.youtube.com/watch?v=cWlagqX0BJQ",
      "embed_url": "https://www.youtube.com/embed/cWlagqX0BJQ",
      "title": "Live : Kedarnath Live Darshan 2025  केदारनाथ लाइव मंदिर से दर्शन || Kedarnath Live Darshan Temple",
      "channel": "Swarg Marg",
      "channel_id": "UC7Uo3euG3IA0yBlQyIXDcUA",
      "viewer_count": 5,
      "is_trusted_channel": false,
      "stream_started_at": "2025-05-11T22:17:52Z",
      "published_at": "2025-05-11T22:10:43Z",
      "thumbnail": "https://i.ytimg.com/vi/cWlagqX0BJQ/hqdefault_live.jpg"
    },
    {
      "temple_id": "jagannath",
      "temple_name": "Jagannath Puri",
      "video_id": "KJh4xlck7-E",
      "url": "https://www.youtube.com/watch?v=KJh4xlck7-E",
      "embed_url": "https://www.youtube.com/embed/KJh4xlck7-E",
      "title": "🔴 Live : GharSabha-2129 @ Khatmuhurt Mahotsav Jagannathpuri | 09/02/2026 | Swami Nityaswarupdasji",
      "channel": "Sardhar Katha",
      "channel_id": "UCQhp381aq84txyUYNJ-1sDw",
      "viewer_count": 377,
      "is_trusted_channel": false,
      "stream_started_at": "2026-02-09T14:58:17Z",
      "published_at": "2026-02-09T14:20:46Z",
      "thumbnail": "https://i.ytimg.com/vi/KJh4xlck7-E/hqdefault_live.jpg"
    },
    {
      "temple_id": "vishwanath",
      "temple_name": "Kashi Vishwanath",
      "video_id": "RR6rhXFZ9ac",
      "url": "https://www.youtube.com/watch?v=RR6rhXFZ9ac",
      "embed_url": "https://www.youtube.com/embed/RR6rhXFZ9ac",
      "title": "🔴Live Darshan From Shree Kashi Vishwanath Temple Varanasi ( श्री काशी विश्वनाथ मंदिर से लाइव दर्शन )",
      "channel": "BHAKTI LIVE",
      "channel_id": "UCXhail7h5FDRbHprlR56nIw",
      "viewer_count": 12,
      "is_trusted_channel": false,
      "stream_started_at": "2026-02-09T10:27:15Z",
      "published_at": "2026-02-09T10:24:24Z",
      "thumbnail": "https://i.ytimg.com/vi/RR6rhXFZ9ac/hqdefault_live.jpg"
    },
    {
      "temple_id": "tirupati",
      "temple_name": "Tirumala Tirupati Balaji",
      "video_id": "eTWaPQW7rdk",
      "url": "https://www.youtube.com/watch?v=eTWaPQW7rdk",
      "embed_url": "https://www.youtube.com/embed/eTWaPQW7rdk",
      "title": "|| SVBC LIVE STREAMING || SVBC TTD",
      "channel": "SVBC TTD",
      "channel_id": "UCS2Y83GD-fc7qqgNW5uj41g",
      "viewer_count": 567,
      "is_trusted_channel": true,
      "stream_started_at": "2026-01-05T20:37:27Z",
      "published_at": "2026-01-05T16:26:03Z",
      "thumbnail": "https://i.ytimg.com/vi/eTWaPQW7rdk/hqdefault_live.jpg"
    },
    {
      "temple_id": "vaishno_devi",
      "temple_name": "Vaishno Devi",
      "video_id": "C_SZSdeA4rA",
      "url": "https://www.youtube.com/watch?v=C_SZSdeA4rA",
      "embed_url": "https://www.youtube.com/embed/C_SZSdeA4rA",
      "title": "Live :- माँ वैष्णों देवी लाइव दर्शन | Maa Vaishno Devi Aarti From Bhawan~माता वैष्णो देवी आरती,वंदना",
      "channel": "Radha Madhav Bhakti",
      "channel_id": "UC5SVw4I1kK4xB0h60Tdk5lQ",
      "viewer_count": 6,
      "is_trusted_channel": false,
      "stream_started_at": "2026-02-05T12:14:42Z",
      "published_at": "2026-02-05T07:19:45Z",
      "thumbnail": "https://i.ytimg.com/vi/C_SZSdeA4rA/hqdefault_live.jpg"
    },
    {
      "temple_id": "golden_temple",
      "temple_name": "Golden Temple Amritsar",
      "video_id": "7bEpr1vNpMI",
      "url": "https://www.youtube.com/watch?v=7bEpr1vNpMI",
      "embed_url": "https://www.youtube.com/embed/7bEpr1vNpMI",
      "title": "LIVE GURBANI 09.02.26 | Gurbani Kirtan Live | #livegurbani #live  Live  Daily waheguru ji",
      "channel": "Sur Simran Gurbani",
      "channel_id": "UC5Avhz91GejfLe4sRjm0vhg",
      "viewer_count": 155,
      "is_trusted_channel": false,
      "stream_started_at": "2026-02-08T23:33:16Z",
      "published_at": "2026-02-08T15:53:26Z",
      "thumbnail": "https://i.ytimg.com/vi/7bEpr1vNpMI/hqdefault_live.jpg"
    }
  ]
}